refextract_cli/__init__.py
refextract_cli/cli.py
refextract_cli-0.1.2.dist-info/LICENSE
refextract_cli-0.1.2.dist-info/METADATA
refextract_cli-0.1.2.dist-info/WHEEL
refextract_cli-0.1.2.dist-info/entry_points.txt
refextract_cli-0.1.2.dist-info/top_level.txt
refextract_cli-0.1.2.dist-info/RECORD
