Metadata-Version: 2.1
Name: refextract-cli
Version: 0.1.2
Summary: Command line interface for refextract
License-File: LICENSE
Requires-Dist: refextract (==1.1.4)
Requires-Dist: rich (==13.3.4)
